LICENSE
near_seed_phrase/__init__.py
near_seed_phrase/main.py
near_seed_phrase/utils/__init__.py
near_seed_phrase/utils/hd_key.py
near_seed_phrase/utils/near_keys.py
near_seed_phrase/utils/seed_phrase.py
near_seed_phrase_py-0.1.2.dist-info/LICENSE
near_seed_phrase_py-0.1.2.dist-info/WHEEL
near_seed_phrase_py-0.1.2.dist-info/METADATA
near_seed_phrase_py-0.1.2.dist-info/RECORD
