Metadata-Version: 2.1
Name: near-seed-phrase-py
Version: 0.1.2
Summary: Python tool for creating and converting mnemonic-phrases, public key and private key for NEAR accounts.
Home-page: https://github.com/lachlanglen/near-seed-phrase-py
License: MIT
Keywords: near,seedphrase,seed,phrase,python
Author: Lachlan Glen
Author-email: lachlanjglen@gmail.com
Requires-Python: >=3.9,<4.0
Classifier: License :: OSI Approved :: MIT License
Classifier: Programming Language :: Python :: 3
Classifier: Programming Language :: Python :: 3.9
Classifier: Programming Language :: Python :: 3.10
Classifier: Programming Language :: Python :: 3.11
Requires-Dist: base58 (>=2.1.1,<3.0.0)
Requires-Dist: mnemonic (>=0.20,<0.21)
Requires-Dist: pynacl (>=1.5.0,<2.0.0)
Project-URL: Repository, https://github.com/lachlanglen/near-seed-phrase-py
